perctest/__init__.py
perctest/__main__.py
perctest-1.0.3.dist-info/DESCRIPTION.rst
perctest-1.0.3.dist-info/METADATA
perctest-1.0.3.dist-info/RECORD
perctest-1.0.3.dist-info/WHEEL
perctest-1.0.3.dist-info/entry_points.txt
perctest-1.0.3.dist-info/metadata.json
perctest-1.0.3.dist-info/top_level.txt
