Metadata-Version: 2.0
Name: perctest
Version: 1.0.3
Summary: A unit testing library for python3
Home-page: UNKNOWN
Author: ThePerkinrex
Author-email: theperkinrex@gmail.com
License: UNKNOWN
Keywords: unit-testing
Platform: UNKNOWN
Classifier: Development Status :: 3 - Alpha
Classifier: Intended Audience :: Developers
Classifier: Topic :: Software Development :: Build Tools
Classifier: License :: OSI Approved :: MIT License
Classifier: Programming Language :: Python :: 3
Classifier: Programming Language :: Python :: 3.4
Classifier: Programming Language :: Python :: 3.5
Classifier: Programming Language :: Python :: 3.6
Requires-Python: >=3
